README.md
setup.py
Fibo/__init__.py
Fibo/fibo.py
Fibo/multi_fibo.py
Fibo/cmd/__init__.py
Fibo/cmd/fibo_cmd.py
fibo_py_aesc.egg-info/PKG-INFO
fibo_py_aesc.egg-info/SOURCES.txt
fibo_py_aesc.egg-info/dependency_links.txt
fibo_py_aesc.egg-info/entry_points.txt
fibo_py_aesc.egg-info/top_level.txt