Metadata-Version: 2.1
Name: fibo-py-aesc
Version: 0.1.0
Summary: Calculates a Fibonacci Number
Home-page: https://github.com/aeklant/fibo.git
Author: Abraham Escalante
License: UNKNOWN
Platform: UNKNOWN
Classifier: Development Status :: 4 - Beta
Classifier: Programming Language :: Python :: 3
Classifier: Operating System :: OS Independent
Requires-Python: >=3
